odoo9_addon_base_geoengine_demo-9.0.1.0.0.99.dev1-py2.7-nspkg.pth
odoo_addons/base_geoengine_demo/__openerp__.py
odoo_addons/base_geoengine_demo/zip_view.xml
odoo_addons/base_geoengine_demo/retail_machine.py
odoo_addons/base_geoengine_demo/geo_npa.py
odoo_addons/base_geoengine_demo/__init__.py
odoo_addons/base_geoengine_demo/retail_machine_view.xml
odoo_addons/base_geoengine_demo/README.rst
odoo_addons/base_geoengine_demo/security/ir.model.access.csv
odoo_addons/base_geoengine_demo/data/retail_machine_geom.xml
odoo_addons/base_geoengine_demo/data/npa_geom.xml
odoo_addons/base_geoengine_demo/images/map-hover.png
odoo_addons/base_geoengine_demo/images/map.png
odoo_addons/base_geoengine_demo/static/description/icon.png
odoo9_addon_base_geoengine_demo-9.0.1.0.0.99.dev1.dist-info/top_level.txt
odoo9_addon_base_geoengine_demo-9.0.1.0.0.99.dev1.dist-info/WHEEL
odoo9_addon_base_geoengine_demo-9.0.1.0.0.99.dev1.dist-info/RECORD
odoo9_addon_base_geoengine_demo-9.0.1.0.0.99.dev1.dist-info/metadata.json
odoo9_addon_base_geoengine_demo-9.0.1.0.0.99.dev1.dist-info/DESCRIPTION.rst
odoo9_addon_base_geoengine_demo-9.0.1.0.0.99.dev1.dist-info/METADATA
odoo9_addon_base_geoengine_demo-9.0.1.0.0.99.dev1.dist-info/namespace_packages.txt
