Metadata-Version: 2.0
Name: odoo9-addon-base-geoengine-demo
Version: 9.0.1.0.0.99.dev1
Summary: Geo spatial support Demo
Home-page: http://openerp.camptocamp.com
Author: UNKNOWN
Author-email: UNKNOWN
License: AGPL-3
Platform: UNKNOWN
Requires-Dist: odoo (<9.1a,>=9.0a)
Requires-Dist: odoo9-addon-base-geoengine
Classifier: Programming Language :: Python :: 2.7
Classifier: Framework :: Odoo
Classifier: License :: OSI Approved :: GNU Affero General Public License v3
